MANIFEST.in
setup.py
django_klaus.egg-info/PKG-INFO
django_klaus.egg-info/SOURCES.txt
django_klaus.egg-info/dependency_links.txt
django_klaus.egg-info/not-zip-safe
django_klaus.egg-info/requires.txt
django_klaus.egg-info/top_level.txt
klaus/__init__.py
klaus/diff.py
klaus/markup.py
klaus/repo.py
klaus/urls.py
klaus/utils.py
klaus/views.py
klaus/static/klaus/klaus.css
klaus/static/klaus/line-highlighter.js
klaus/static/klaus/pygments.css
klaus/templates/klaus/base.html
klaus/templates/klaus/history.html
klaus/templates/klaus/repo_list.html
klaus/templates/klaus/skeleton.html
klaus/templates/klaus/view_blob.html
klaus/templates/klaus/view_commit.html
klaus/templates/klaus/includes/not_shown.html
klaus/templates/klaus/includes/pagination.html
klaus/templates/klaus/includes/tree.inc.html
klaus/templatetags/__init__.py
klaus/templatetags/__init__.pyc
klaus/templatetags/klaus.py
klaus/templatetags/klaus.pyc