Metadata-Version: 1.1
Name: django-klaus
Version: 0.1.1
Summary: Git web viewer app for django.
Home-page: https://github.com/biern/django-klaus
Author: Marcin Biernat, Jonas Haag
Author-email: mb@marcinbiernat.pl, jonas@lophus.org
License: UNKNOWN
Platform: UNKNOWN
Classifier: Topic :: Internet :: WWW/HTTP :: Dynamic Content
Classifier: Topic :: Internet :: WWW/HTTP :: WSGI :: Application
Classifier: Topic :: Software Development :: Version Control
Classifier: Environment :: Web Environment
Classifier: Intended Audience :: Developers
Classifier: License :: OSI Approved :: ISC License (ISCL)
Classifier: Programming Language :: Python
Classifier: Programming Language :: Python :: 2.6
Classifier: Programming Language :: Python :: 2.7
